{"is_source_file": false, "format": "", "description": "", "external_files": [], "external_methods": [], "published": [], "classes": [], "methods": [], "calls": [], "search-terms": [], "state": 2, "file_id": 4, "knowledge_revision": 56, "git_revision": "5588f8fc0b42f3b9de897b471d0259940a86082c", "hash": "c14fda5038896c7963dae02c8b1c3e66", "format-version": 4, "code-base-name": "todo_frontend", "filename": "todo_frontend/src/App.css", "revision_history": [{"56": "5588f8fc0b42f3b9de897b471d0259940a86082c"}]}